simplearg/__init__.py
simplearg/simple_arg_parser.py
simplearg/version.py
simplearg-0.0.1a0.dist-info/LICENSE
simplearg-0.0.1a0.dist-info/METADATA
simplearg-0.0.1a0.dist-info/WHEEL
simplearg-0.0.1a0.dist-info/top_level.txt
simplearg-0.0.1a0.dist-info/RECORD
